heroes_build_scrapper/__init__.py
heroes_build_scrapper/data.py
heroes_build_scrapper/scrapping.py
heroes_build_scrapper/utils.py
heroes_build_scrapper-1.2.dist-info/LICENSE
heroes_build_scrapper-1.2.dist-info/METADATA
heroes_build_scrapper-1.2.dist-info/WHEEL
heroes_build_scrapper-1.2.dist-info/top_level.txt
heroes_build_scrapper-1.2.dist-info/RECORD
