Metadata-Version: 2.1
Name: heroes-build-scrapper
Version: 1.2
Summary: A library for scraping builds for Heroes of the Storm heroes.
Home-page: UNKNOWN
Author: Gabriel Cruz
Author-email: gabs.oficial98@gmail.com
License: UNKNOWN
Platform: UNKNOWN
Requires-Dist: beautifulsoup4 (==4.6.3)
Requires-Dist: bs4 (==0.0.1)
Requires-Dist: certifi (==2018.8.24)
Requires-Dist: chardet (==3.0.4)
Requires-Dist: idna (==2.7)
Requires-Dist: requests (==2.19.1)
Requires-Dist: urllib3 (==1.23)
